Workbook

Sheet QA
D3: PARTICULARS | E3: MAXX CITY 1.3 LX BS6.2 - (8.2 Feet )
D4: Ex Showroom | E4: =VLOOKUP($E$3,PRICE!A:J,2,0) -> 808500
D5: Insurance | E5: =VLOOKUP($E$3,PRICE!A:J,3,0) -> 27736.567 | H5: PARTICULARS | I5: =E3 -> MAXX CITY 1.3 LX BS6.2 - (8.2 Feet )
D6: KA Life Tax | E6: =VLOOKUP($E$3,PRICE!A:J,4,0) -> 69227.8 | H6: Ex Showroom | I6: =E4 -> 808500
D7: Temp | E7: =VLOOKUP($E$3,PRICE!A:J,5,0) -> 2524.121 | H7: Insurance | I7: =E5 -> 27736.567
D8: RSA | E8: =VLOOKUP($E$3,PRICE!A:J,6,0) -> 1698 | H8: E PAYMENT | I8: =E6 -> 69227.8
D9: Yellow Paint & Handling | E9: =VLOOKUP($E$3,PRICE!A:J,7,0) -> 3100 | H9: Total Cost | I9: =SUM(I6:I8) -> 905464.37
D10: Fast Tag | E10: =VLOOKUP($E$3,PRICE!A:J,8,0) -> 600
D11: Accessories | E11: =VLOOKUP($E$3,PRICE!A:J,9,0) -> 5000
D12: TCS 1 % | E12: =VLOOKUP($E$3,PRICE!A:J,10,0) -> 0
D13: Body bulding | E13: 0
D14: Total Cost | E14: =SUM(E4:E13) -> 918386.49
D15: Discount | E15: 20333
D16: RTO CHARGES | E16: 8000
D17: FINAL COST | E17: =+E14-G17 -> 890053.49 | G17: =+E16+E15 -> 28333 | H17: 1.5 | I17: LIFE TAX
H18: 1.5 | I18: E PAYEMNT
D19: =D3 -> PARTICULARS | E19: =E3 -> MAXX CITY 1.3 LX BS6.2 - (8.2 Feet )
D20: =D4 -> Ex Showroom | E20: =E4 -> 808500
D21: =D5 -> Insurance | E21: =E5 -> 27736.567
D22: E PAYMENT | E22: =E6 -> 69227.8
D23: =D12 -> TCS 1 % | E23: =E12 -> 0
D24: Total Cost | E24: =SUM(E20:E23) -> 905464.37

Sheet Sheet1
A1: HDFC | B1: HDFC BANK LTD
A2: CHOLA | B2: CHOLAMANDALAM INVESTMENT AND FINANCE COMPANY LTD
A3: SUNDARAM | B3: SUNDARAM FINANCE LIMITED
A4: HINDUJA | B4: HINDUJA LEYLAND FINANCE LTD
A5: SRI | B5: SHRIRAM FINANCE LIMITED
A6: MFSL | B6: MAHINDRA AND MAHINDRA FINANCIAL SERVICES LTD
A7: HDB | B7: HDB FINANCIAL SERVICES LIMITED
A8: KOTAK | B8: KOTAK MAHINDRA BANK LIMITED
A9: EQUITAS | B9: EQUITAS SMALL FINANCE BANK LTD
A10: GOVE | B10: GOVE FINANCE LTD
A11: ICIC | B11: ICICI BANK LIMITED
A12: INDOSTAR CAPITAL | B12: INDOSTAR CAPITAL FINANCE LTD
A13: KARUR VYSYA | B13: THE KARUR VYSYA BANK LIMITED
A14: YES | B14: 10
A15: KVB | B15: KARUR VYSYA BANK LIMITED
A16: IND | B16: INDIAN BANK
A17: HDB | B17: HDB FINANCIAL SERVICES LIMITED
A18: BOI | B18: BANK OF INDIA
A19: INDS | B19: INDUSIND BANK LTD
A20: SBI | B20: STATE BANK OF INDIA
A21: TMB | B21: TAMILNAD MERCANTILE BANK LTD
B22: SRINIDHI FINANCE LTD
A23: IDFC | B23: IDFC FIRST BANK LIMITED
B24: Tamilnad Mercantile Bank
B25: Union Bank of India
B26: CANARA BANK
B27: Bajaj Finance
B28: City Union Bank
B29: Tata Capital Ltd
B30: MAHAVEER FINANCE INDIA LIMITED
B31: Federal Bank
A32: BOB | B32: Bank of Baroda
B33: AU SMALL FINANCE BANK LIMITED
B34: South Indian Bank
B35: SMFG India Credit Company Limited
B36: hinduja leyland finance

Sheet PRICE
A1: Model | B1: Ex Showroom | C1: Insurance | D1: Life Tax | E1: Temp | F1: RSA | G1: Yellow Paint & Handling | H1: Fast Tag | I1: Accessories | J1: TCS 1 %
A2: MAXX CITY 1.3 LX BS6.2 - (8.2 Feet ) | B2: 808500 | C2: 27736.567 | D2: 69227.8 | E2: 2524.121 | F2: 1698 | G2: 3100 | H2: 600 | I2: 5000 | J2: 0
A3: MAXX CITY 1.3 LX CBC BS6.2 - (8.2 Feet ) | B3: 799500 | C3: 27648.165 | D3: 68500.6 | E3: 2500.487 | F3: 1698 | G3: 3100 | H3: 600 | I3: 5000 | J3: 0
A4: MAXX CITY 1.3 MXi BS6.2 | B4: 838500 | C4: 28031.241 | D4: 71651.8 | E4: 2602.901 | F4: 1698 | G4: 3100 | H4: 600 | I4: 5000 | J4: 0
A5: MAXX CITY 1.3 SXi AC BS6.2 -(8.2 Feet ) | B5: 833500 | C5: 27982.129 | D5: 71247.8 | E5: 2589.771 | F5: 1698 | G5: 3100 | H5: 600 | I5: 5000 | J5: 0
A6: MAXX CITY 1.3 VXi AC BS6.2 -(8.2 Feet ) | B6: 853500 | C6: 28178.579 | D6: 72863.8 | E6: 2642.291 | F6: 1698 | G6: 3100 | H6: 600 | I6: 5000 | J6: 0
A7: MAXX CITY 1.4 LX BS6.2- (8.7 Feet ) | B7: 839500 | C7: 28041.064 | D7: 71732.6 | E7: 2605.527 | F7: 1698 | G7: 3100 | H7: 600 | I7: 5000 | J7: 0
A8: MAXX CITY 1.4 LX CBC BS6.2 - (8.7 Feet ) | B8: 829500 | C8: 27942.839 | D8: 70924.6 | E8: 2579.267 | F8: 1698 | G8: 3100 | H8: 600 | I8: 5000 | J8: 0
A9: MAXX CITY 1.4 MXi BS6.2 | B9: 865500 | C9: 28296.448 | D9: 73833.4 | E9: 2673.803 | F9: 1698 | G9: 3100 | H9: 600 | I9: 5000 | J9: 0
A10: MAXX CITY 1.4 VXi AC BS6.2(8.7 Feet ) | B10: 877500 | C10: 28414.318 | D10: 74803 | E10: 2705.315 | F10: 1698 | G10: 3100 | H10: 600 | I10: 5000 | J10: 0
A11: MAXX CITY LX CNG BS6.2-(8.7 Feet ) | B11: 834500 | C11: 27991.951 | D11: 71328.6 | E11: 2592.397 | F11: 1698 | G11: 3100 | H11: 600 | I11: 5000 | J11: 0
A12: MAXX HD 1.3 LX BS6.2 -(9 Feet ) | B12: 961500 | C12: 29239.407 | D12: 81590.2 | E12: 2925.899 | F12: 1698 | G12: 3300 | H12: 600 | I12: 5000 | J12: 0
A13: MAXX HD 1.3 VXi AC BS6.2--(9 Feet ) | B13: 1013500 | C13: 29750.176 | D13: 85791.8 | E13: 4085.086 | F13: 1698 | G13: 3300 | H13: 600 | I13: 5000 | J13: 10135
... A67: MAHINDRA ZEO V2 DV 200 | B67: 836935 | C67: 25488.519 | D67: 1500 | E67: 400 | F67: 0 | G67: 3100 | H67: 600 | I67: 7500 | J67: 0

Sheet Sheet3
